{
  "version": "7",
  "dialect": "sqlite",
  "entries": [
    {
      "idx": 0,
      "version": "6",
      "when": 1766180557433,
      "tag": "0000_blushing_firebird",
      "breakpoints": true
    },
    {
      "idx": 1,
      "version": "6",
      "when": 1766180871385,
      "tag": "0001_minor_madame_web",
      "breakpoints": true
    },
    {
      "idx": 2,
      "version": "6",
      "when": 1766181724649,
      "tag": "0002_lonely_anthem",
      "breakpoints": true
    },
    {
      "idx": 3,
      "version": "6",
      "when": 1766182128346,
      "tag": "0003_happy_jasper_sitwell",
      "breakpoints": true
    },
    {
      "idx": 4,
      "version": "6",
      "when": 1766319878141,
      "tag": "0004_living_calypso",
      "breakpoints": true
    },
    {
      "idx": 5,
      "version": "6",
      "when": 1781136808144,
      "tag": "0005_feature_tables",
      "breakpoints": true
    }
  ]
}